paskia/__init__.py
paskia/_version.py
paskia/authsession.py
paskia/bootstrap.py
paskia/config.py
paskia/globals.py
paskia/remoteauth.py
paskia/sansio.py
paskia/aaguid/__init__.py
paskia/aaguid/combined_aaguid.json
paskia/db/__init__.py
paskia/db/background.py
paskia/db/jsonl.py
paskia/db/logging.py
paskia/db/migrations.py
paskia/db/operations.py
paskia/db/structs.py
paskia/fastapi/__init__.py
paskia/fastapi/__main__.py
paskia/fastapi/admin.py
paskia/fastapi/api.py
paskia/fastapi/auth_host.py
paskia/fastapi/authz.py
paskia/fastapi/logging.py
paskia/fastapi/mainapp.py
paskia/fastapi/remote.py
paskia/fastapi/reset.py
paskia/fastapi/response.py
paskia/fastapi/session.py
paskia/fastapi/user.py
paskia/fastapi/ws.py
paskia/fastapi/wschat.py
paskia/fastapi/wsutil.py
paskia/frontend-build/auth/index.html
paskia/frontend-build/auth/admin/index.html
paskia/frontend-build/auth/assets/AccessDenied-C29NZI95.css
paskia/frontend-build/auth/assets/AccessDenied-DAdzg_MJ.js
paskia/frontend-build/auth/assets/RestrictedAuth-BOdNrlQB.css
paskia/frontend-build/auth/assets/RestrictedAuth-BSusdAfp.js
paskia/frontend-build/auth/assets/_plugin-vue_export-helper-D2l53SUz.js
paskia/frontend-build/auth/assets/_plugin-vue_export-helper-DYJ24FZK.css
paskia/frontend-build/auth/assets/admin-BeFvGyD6.js
paskia/frontend-build/auth/assets/admin-CmNtuH3s.css
paskia/frontend-build/auth/assets/auth-BKq4T2K2.css
paskia/frontend-build/auth/assets/auth-DvHf8hgy.js
paskia/frontend-build/auth/assets/forward-C86Jm_Uq.js
paskia/frontend-build/auth/assets/helpers-DzjFIx78.js
paskia/frontend-build/auth/assets/pow-2N9bxgAo.js
paskia/frontend-build/auth/assets/reset-B8PlNXuP.css
paskia/frontend-build/auth/assets/reset-D71FG0VL.js
paskia/frontend-build/auth/assets/restricted-CW0drE_k.js
paskia/frontend-build/auth/restricted/index.html
paskia/frontend-build/int/forward/index.html
paskia/frontend-build/int/reset/index.html
paskia/migrate/__init__.py
paskia/migrate/sql.py
paskia-0.10.0.dist-info/METADATA
paskia-0.10.0.dist-info/WHEEL
paskia-0.10.0.dist-info/entry_points.txt
paskia-0.10.0.dist-info/RECORD
