Metadata-Version: 2.4
Name: paskia
Version: 0.10.0
Summary: Passkey Auth made easy: all sites and APIs can be guarded even without any changes on the protected site.
Project-URL: Homepage, https://git.zi.fi/LeoVasanko/paskia
Project-URL: Repository, https://github.com/LeoVasanko/paskia
Author: Leo Vasanko
Keywords: FastAPI,auth_request,forward_auth
Requires-Python: >=3.11
Requires-Dist: aiofiles>=25.1.0
Requires-Dist: base64url>=1.0.0
Requires-Dist: fastapi-vue>=0.3.0
Requires-Dist: fastapi[standard]>=0.104.1
Requires-Dist: jsondiff>=2.2.1
Requires-Dist: msgspec>=0.20.0
Requires-Dist: pyjwt>=2.8.0
Requires-Dist: user-agents>=2.2.0
Requires-Dist: uuid7-standard>=1.0.0
Requires-Dist: webauthn>=1.11.1
Requires-Dist: websockets>=12.0
Provides-Extra: dev
Requires-Dist: coverage[toml]>=7.0.0; extra == 'dev'
Requires-Dist: httpx>=0.27.0; extra == 'dev'
Requires-Dist: pytest-asyncio>=0.24.0; extra == 'dev'
Requires-Dist: pytest>=8.0.0; extra == 'dev'
Requires-Dist: ruff>=0.1.0; extra == 'dev'
Provides-Extra: migrate
Requires-Dist: aiosqlite>=0.19.0; extra == 'migrate'
Requires-Dist: sqlalchemy[asyncio]>=2.0.0; extra == 'migrate'
